<?xml version="1.0" encoding="UTF-8"?>
<bug-controls><model-name>OWASP-Proactives</model-name><version>2013</version><control><id>C2</id><name>Parameterize Queries</name><description><point>-LSB- Untrusted input should be prevented from being interpreted as part of a SQL command Use $ Query Parameterization $ SQL statements are sent to and parsed by the database server separately from any parameters Use defense in depth with use of technologies such as automated static analysis and proper database management system configuration Configure database engines to only support parameterized queries -RSB-</point></description></control><control><id>C3</id><name>Encode Data</name><description><point>-LSB- Encoding is translating special characters into some equivalent form that is no longer dangerous in the target interpreter Manipulating user generated content : ensure that data is filtered and/or encoded when presenting it in the Web View Loading content from an external source : apps that need to display untrusted content inside a Web View should use a dedicated server/host to render and escape HTML/Javascript content in a safe way .</point><point>, This prevents access to local system contents by malicious JavaScript code . -RSB-</point></description></control><control><id>C4</id><name>Validate All Inputs</name><description><point>-LSB- Use two general approaches to performing input syntax validation white listing preferred over black listing Regular expressions offer a way to check whether data matches a specific pattern this is a great way to implement whitelist validation .</point><point>, The security of the application should be enforced where that input is used , e.g. , if input is used to build an HTML response , then the appropriate HTML encoding should be performed to prevent XSS attacks .</point><point>, Also , if input is used to build a SQL statement , Query Parameterization should be used . -RSB-</point></description></control><control><id>C5</id><name>Implement Identity and Authentication Controls</name><description><point>-LSB- Use Multi Factor Authentication For Mobile Application : Token Based Authentication .</point><point>, avoid storing/persisting authentication credentials locally on the device .</point><point>, Instead , perform initial authentication using the username and password supplied by the user , and then generate a shortlived access token which can be used to authenticate a client request without sending the user 's credentials .</point><point>, Implement Secure Password Storage using cryptography controls Implement Secure Password Recovery Mechanism Session : Generation and Expiration : On any successful authentication and reauthentication the software should generate a new session and session id .</point><point>, Mandatory to set expiration timeouts for every session , after a specified period of inactivity .</point><point>, Reauthentication for Sensitive Features -RSB-</point></description></control><control><id>C6</id><name>Implement Access Controls</name><description><point>-LSB- Force All Requests to go Through Access Control Checks Deny by Default Principle of Least Privilege : each user or system component should be allocated the minimum privilege required to perform an action for the minimum amount of time Avoid Hard Coded Access Control Checks : enforcement layer -LRB- checks in code -RRB- and your access control decision making process -LRB- the access control `` engine '' -RRB- should be separated when possible Code to the Activity : Consider checking if the user has access to that feature in code , as opposed to checking what role the user is in code Server side Trusted Data Should Drive Access Control .</point><point>, Policy data such as a user 's role or an access control rule should never be part of the request -RSB-</point></description></control><control><id>C7</id><name>Protect Data</name><description><point>-LSB- Classify and Encrypt Data at rest .</point><point>, Develop your own crypto algorithm &amp; key size should be optly chosen Encrypt Data in Transit .</point><point>, TLS is by far the most common and widely supported model used by web applications for encryption in transit Implement Protection in Transit Mobile Application : Secure Local Storage .</point><point>, Avoid storing the sensitive data &amp; authentication credentials , access token , etc. on local device -RSB-</point></description></control><control><id>C8</id><name>Implement Logging and Intrusion Detection</name><description><point>-LSB- Ensure proper level of logging Follow a common logging approach within the system and across systems where possible to make correlation easy Make sure to always log the timestamp and identifying information like the source IP and userid , but be careful not to log private or confidential data or opt out data or secrets Design proper positioning of IDS sensors and management -RSB-</point></description></control><control><id>C9</id><name>Leverage Security Frameworks and Libraries</name><description><point>-LSB- When possible , the emphasis should be on using the existing secure features of frameworks rather than importing third party libraries .</point><point>, It is preferable to have developers take advantage of what they 're already using instead of forcing yet another library on them Not all the frameworks are completely secured hence it is important to build in additional security where possible , updating frequently and verifying them for security early and often like any other software you depend upon -RSB-</point></description></control><control><id>C10</id><name>Errors and exceptions handling</name><description><point>-LSB- It is recommended to manage exceptions in a centralized manner to avoid duplicated try/catch blocks in the code , and to ensure that all unexpected behaviors are correctly handled inside the application .</point><point>, Ensure that error messages displayed to users do not leak critical data , but are still verbose enough to explain the issue to the user .</point><point>, Ensure that exceptions are logged in a way that gives enough information for Q/A , forensics or incident response teams to understand the problem . -RSB-</point></description></control></bug-controls>